morphocut/__init__.py
morphocut/_optional.py
morphocut/_version.py
morphocut/annotation.py
morphocut/core.py
morphocut/file.py
morphocut/image.py
morphocut/pandas.py
morphocut/parallel.py
morphocut/pims.py
morphocut/str.py
morphocut/stream.py
morphocut/torch.py
morphocut/vignetting.py
morphocut/contrib/ecotaxa.py
morphocut/contrib/zooprocess.py
morphocut/pipeline/__init__.py
morphocut/pipeline/base.py
morphocut/pipeline/object_scale.py
morphocut-0.1.2.dist-info/AUTHORS.rst
morphocut-0.1.2.dist-info/LICENSE.md
morphocut-0.1.2.dist-info/METADATA
morphocut-0.1.2.dist-info/WHEEL
morphocut-0.1.2.dist-info/top_level.txt
morphocut-0.1.2.dist-info/RECORD
