Metadata-Version: 2.1
Name: morphocut
Version: 0.1.2
Summary: Image processing pipeline
Home-page: https://github.com/morphocut/morphocut
Author: Simon-Martin Schroeder
Author-email: martin.schroeder@nerdluecht.de
License: UNKNOWN
Platform: UNKNOWN
Classifier: Programming Language :: Python :: 3
Classifier: Programming Language :: Python :: 3.6
Classifier: Programming Language :: Python :: 3.7
Classifier: License :: OSI Approved :: MIT License
Classifier: Operating System :: OS Independent
Classifier: Development Status :: 3 - Alpha
Classifier: Intended Audience :: Science/Research
Requires-Python: >=3.6
Requires-Dist: numpy
Requires-Dist: scikit-image (>=0.16.0)
Requires-Dist: pandas
Requires-Dist: tqdm
Requires-Dist: scipy
Provides-Extra: docs
Requires-Dist: sphinx (~=2.2) ; extra == 'docs'
Requires-Dist: sphinx-rtd-theme ; extra == 'docs'
Requires-Dist: sphinxcontrib-programoutput ; extra == 'docs'
Requires-Dist: sphinx-autodoc-typehints (>=1.10.0) ; extra == 'docs'
Provides-Extra: tests
Requires-Dist: pytest ; extra == 'tests'
Requires-Dist: pytest-cov ; extra == 'tests'
Requires-Dist: timer-cm ; extra == 'tests'
Requires-Dist: parse ; extra == 'tests'
